Workbook

Sheet Datos_Originales
A1: Datos originales — transcripción literal de las imágenes recibidas
A2: Texto y orden conservados tal como aparecen en las imágenes. Sin cálculos en esta hoja.
A4: Imagen 1 — Detalle de alquileres (columnas B, C, D de la captura)
A5: Columna B | B5: Columna C | C5: Columna D
B6: Edificio de departamentos
B7: Tercer piso
A8: Inquilino | B8: 2 dorm. | C8: 1500000
A9: Inquilino | B9: 2 dorm. | C9: 1500000
A10: Inquilino | B10: 1 dorm. | C10: 1200000
A11: Inquilino | B11: 1 dorm. | C11: 1100000
B12: Segundo piso
A13: Inquilino | B13: 2 dorm. | C13: 1600000
A14: Inquilino | B14: 2 dorm. | C14: 1500000
A15: Inquilino | B15: 2 dorm. | C15: 1500000
A16: Inquilino | B16: 2 dorm. | C16: 1500000
A17: Inquilino | B17: 1 dorm. | C17: 1250000
B18: Primer piso
A19: Inquilino | B19: 1 dorm. | C19: 1300000
A20: Inquilino | B20: 3 dorm. | C20: 1600000
B21: Planta Baja
A22: Inquilino | B22: 1 dorm. | C22: 1200000
A23: Inquilino | B23: 1 dorm. | C23: 900000
A24: Inquilino | B24: Cochera | C24: 700000
A25: Inquilino | B25: Cochera y dpto | C25: 1200000
B26: TOTAL | C26: 19550000
A27: Cambio | B27: 6100 | C27: 3205
A28: Nota: la última fila de la captura muestra 'Cambio | 6100 | ₲ 3.205'; el '₲' delante de 3.205 es de la fuente (es un valor en USD).
A30: Imagen 2 — Planilla 'RENTABILIDAD EDIFICIO DE APARTAMENTOS'
A31: Precio USD | B31: Renta Anual | C31: USD Mensual | D31: Gs Mensual | E31: Cambio / USD Anual
A32: 340000 | B32: Bruta (11,3%) | C32: 3205 | D32: 19550000 | E32: 6100 / 38.459
B33: Impuesto anual | C33: 2764 | E33: 2.764
B34: Gastos anuales | C34: 1200 | E34: 1.200
B35: Renta Neta | E35: 34.495
B36: Renta Anual Neta | C36: 10,15%
A37: 340.000 | 100% | 34.495 | B37: 34.495 | X | 340.000 | E37: (regla de tres de la fuente)
A38: Nota: en la planilla, 'Impuesto anual' y 'Gastos anuales' aparecen en la columna 'USD Mensual' pero sus valores son anuales (se repiten en 'USD Anual').

Sheet Alquileres_Unidad
A1: Alquileres por unidad — transcripción estructurada (estado: TRANSCRITO, no verificado)
A2: Leyenda: azul = dato recibido (fuente: imágenes enviadas 2026-10-02); negro = fórmula; verde = vínculo a otra hoja; rojo itálica = PENDIENTE de confirmar (no es cero).
A4: N° | B4: Ref. provisoria | C4: Piso | D4: Texto original (col. C) | E4: Tipología | F4: Concepto | G4: Moneda | H4: Alquiler mensual (Gs) | I4: Equivalente USD (TC planilla) | J4: Estado de verificación | K4: Observación
A5: 1 | B5: P3-01 | C5: Tercer piso | D5: 2 dorm. | E5: 2 dormitorios | F5: Departamento | G5: PYG | H5: 1500000 | I5: =H5/Parametros!$B$6 -> 245.90164 | J5: Transcrito — sin contrato ni comprobante de cobro
A6: 2 | B6: P3-02 | C6: Tercer piso | D6: 2 dorm. | E6: 2 dormitorios | F6: Departamento | G6: PYG | H6: 1500000 | I6: =H6/Parametros!$B$6 -> 245.90164 | J6: Transcrito — sin contrato ni comprobante de cobro
A7: 3 | B7: P3-03 | C7: Tercer piso | D7: 1 dorm. | E7: 1 dormitorio | F7: Departamento | G7: PYG | H7: 1200000 | I7: =H7/Parametros!$B$6 -> 196.72131 | J7: Transcrito — sin contrato ni comprobante de cobro
A8: 4 | B8: P3-04 | C8: Tercer piso | D8: 1 dorm. | E8: 1 dormitorio | F8: Departamento | G8: PYG | H8: 1100000 | I8: =H8/Parametros!$B$6 -> 180.32787 | J8: Transcrito — sin contrato ni comprobante de cobro
A9: 5 | B9: P2-01 | C9: Segundo piso | D9: 2 dorm. | E9: 2 dormitorios | F9: Departamento | G9: PYG | H9: 1600000 | I9: =H9/Parametros!$B$6 -> 262.29508 | J9: Transcrito — sin contrato ni comprobante de cobro
A10: 6 | B10: P2-02 | C10: Segundo piso | D10: 2 dorm. | E10: 2 dormitorios | F10: Departamento | G10: PYG | H10: 1500000 | I10: =H10/Parametros!$B$6 -> 245.90164 | J10: Transcrito — sin contrato ni comprobante de cobro
A11: 7 | B11: P2-03 | C11: Segundo piso | D11: 2 dorm. | E11: 2 dormitorios | F11: Departamento | G11: PYG | H11: 1500000 | I11: =H11/Parametros!$B$6 -> 245.90164 | J11: Transcrito — sin contrato ni comprobante de cobro
A12: 8 | B12: P2-04 | C12: Segundo piso | D12: 2 dorm. | E12: 2 dormitorios | F12: Departamento | G12: PYG | H12: 1500000 | I12: =H12/Parametros!$B$6 -> 245.90164 | J12: Transcrito — sin contrato ni comprobante de cobro
A13: 9 | B13: P2-05 | C13: Segundo piso | D13: 1 dorm. | E13: 1 dormitorio | F13: Departamento | G13: PYG | H13: 1250000 | I13: =H13/Parametros!$B$6 -> 204.91803 | J13: Transcrito — sin contrato ni comprobante de cobro
A14: 10 | B14: P1-01 | C14: Primer piso | D14: 1 dorm. | E14: 1 dormitorio | F14: Departamento | G14: PYG | H14: 1300000 | I14: =H14/Parametros!$B$6 -> 213.11475 | J14: Transcrito — sin contrato ni comprobante de cobro
A15: 11 | B15: P1-02 | C15: Primer piso | D15: 3 dorm. | E15: 3 dormitorios | F15: Departamento | G15: PYG | H15: 1600000 | I15: =H15/Parametros!$B$6 -> 262.29508 | J15: Transcrito — sin contrato ni comprobante de cobro
A16: 12 | B16: PB-01 | C16: Planta baja | D16: 1 dorm. | E16: 1 dormitorio | F16: Departamento | G16: PYG | H16: 1200000 | I16: =H16/Parametros!$B$6 -> 196.72131 | J16: Transcrito — sin contrato ni comprobante de cobro
A17: 13 | B17: PB-02 | C17: Planta baja | D17: 1 dorm. | E17: 1 dormitorio | F17: Departamento | G17: PYG | H17: 900000 | I17: =H17/Parametros!$B$6 -> 147.54098 | J17: Transcrito — sin contrato ni comprobante de cobro
A18: 14 | B18: PB-03 | C18: Planta baja | D18: Cochera | E18: No aplica | F18: Cochera | G18: PYG | H18: 700000 | I18: =H18/Parametros!$B$6 -> 114.7541 | J18: Transcrito — sin contrato ni comprobante de cobro | K18: Concepto no incluido en el mix comercial informado (13 dptos + 1 local). Confirmar qué es y si está incluido en el precio.
A19: 15 | B19: PB-04 | C19: Planta baja | D19: Cochera y dpto | E19: A confirmar | F19: Mixto — a confirmar | G19: PYG | H19: 1200000 | I19: =H19/Parametros!$B$6 -> 196.72131 | J19: Transcrito — sin contrato ni comprobante de cobro | K19: NO interpretado como local comercial ni como unidad adicional. Confirmar a qué unidad corresponde y si agrupa o duplica ingresos.
G20: TOTAL | H20: =SUM(H5:H19) -> 19550000 | I20: =SUM(I5:I19) -> 3204.918
A22: La 'Ref. provisoria' es un identificador de trabajo de Meridiano según el orden de la captura; no corresponde a la numeración real de las unidades (no informada).
A23: Ningún dato de inquilinos (nombres, contactos) se registra en este archivo: la fuente solo dice 'Inquilino'.

Sheet Conciliacion
A1: Conciliación — composición informada vs. detalle de alquileres
A2: Leyenda: azul = dato recibido (fuente: imágenes enviadas 2026-10-02); negro = fórmula; verde = vínculo a otra hoja; rojo itálica = PENDIENTE de confirmar (no es cero).
A4: Concepto | B4: Mix comercial informado | C4: Filas en el detalle | D4: Diferencia | E4: Resultado | F4: Observación
A5: Departamentos 1 dormitorio | B5: =Parametros!$B$16 -> 6 | C5: =COUNTIFS(Alquileres_Unidad!$E$5:$E$19,"1 dormitorio") -> 6 | D5: =C5-B5 -> 0 | E5: =IF(D5=0,"Coincide","DIFERENCIA") -> Coincide
A6: Departamentos 2 dormitorios | B6: =Parametros!$B$17 -> 6 | C6: =COUNTIFS(Alquileres_Unidad!$E$5:$E$19,"2 dormitorios") -> 6 | D6: =C6-B6 -> 0 | E6: =IF(D6=0,"Coincide","DIFERENCIA") -> Coincide
A7: Departamentos 3 dormitorios | B7: =Parametros!$B$18 -> 1 | C7: =COUNTIFS(Alquileres_Unidad!$E$5:$E$19,"3 dormitorios") -> 1 | D7: =C7-B7 -> 0 | E7: =IF(D7=0,"Coincide","DIFERENCIA") -> Coincide
A8: Local comercial | B8: =Parametros!$B$19 -> 1 | C8: =COUNTIFS(Alquileres_Unidad!$F$5:$F$19,"Local comercial") -> 0 | D8: =C8-B8 -> -1 | E8: =IF(D8=0,"Coincide","DIFERENCIA") -> DIFERENCIA | F8: El local comercial no aparece identificado expresamente en el detalle.
A9: Cochera (sola) | B9: 0 | C9: =COUNTIFS(Alquileres_Unidad!$F$5:$F$19,"Cochera") -> 1 | D9: =C9-B9 -> 1 | E9: =IF(D9=0,"Coincide","DIFERENCIA") -> DIFERENCIA | F9: Concepto no mencionado en la composición comercial.
A10: 'Cochera y dpto' (concepto mixto) | B10: 0 | C10: =COUNTIFS(Alquileres_Unidad!$F$5:$F$19,"Mixto — a confirmar") -> 1 | D10: =C10-B10 -> 1 | E10: =IF(D10=0,"Coincide","DIFERENCIA") -> DIFERENCIA | F10: Si incluye un departamento, el total de dptos sería 14, no 13.
A11: Total departamentos (filas 'Departamento') | B11: =SUM(B5:B7) -> 13 | C11: =COUNTIFS(Alquileres_Unidad!$F$5:$F$19,"Departamento") -> 13 | D11: =C11-B11 -> 0 | E11: =IF(D11=0,"Coincide","DIFERENCIA") -> Coincide | F11: Las 13 filas con tipología coinciden con el mix 6 + 6 + 1.
A13: Control de suma del detalle
A14: Control | B14: Valor | E14: Resultado | F14: Observación
A15: Suma recalculada de las 15 filas (Gs) | B15: =Alquileres_Unidad!H20 -> 19550000
A16: Total indicado en la fuente (Gs) | B16: =Parametros!$B$7 -> 19550000
A17: Diferencia (Gs) | B17: =B15-B16 -> 0 | E17: =IF(B17=0,"Suma correcta","DIFERENCIA") -> Suma correcta | F17: Verifica la aritmética, no la composición ni el cobro efectivo.
A19: Subtotal por piso (Gs)
A20: Piso | B20: Filas | C20: Alquiler mensual (Gs) | D20: % del total | F20: Observación
A21: Tercer piso | B21: =COUNTIFS(Alquileres_Unidad!$C$5:$C$19,A21) -> 4 | C21: =SUMIFS(Alquileres_Unidad!$H$5:$H$19,Alquileres_Unidad!$C$5:$C$19,A21) -> 5300000 | D21: =C21/$C$25 -> 0.27109974
A22: Segundo piso | B22: =COUNTIFS(Alquileres_Unidad!$C$5:$C$19,A22) -> 5 | C22: =SUMIFS(Alquileres_Unidad!$H$5:$H$19,Alquileres_Unidad!$C$5:$C$19,A22) -> 7350000 | D22: =C22/$C$25 -> 0.37595908
A23: Primer piso | B23: =COUNTIFS(Alquileres_Unidad!$C$5:$C$19,A23) -> 2 | C23: =SUMIFS(Alquileres_Unidad!$H$5:$H$19,Alquileres_Unidad!$C$5:$C$19,A23) -> 2900000 | D23: =C23/$C$25 -> 0.1483376
A24: Planta baja | B24: =COUNTIFS(Alquileres_Unidad!$C$5:$C$19,A24) -> 4 | C24: =SUMIFS(Alquileres_Unidad!$H$5:$H$19,Alquileres_Unidad!$C$5:$C$19,A24) -> 4000000 | D24: =C24/$C$25 -> 0.20460358
A25: Total | B25: =SUM(B21:B24) -> 15 | C25: =SUM(C21:C24) -> 19550000 | D25: =SUM(D21:D24) -> 1
A27: Estado de la conciliación
A28: =IF(AND(B17=0,D8=0),"CONCILIADA","PRELIMINAR — composición no conciliada (ver preguntas abajo)") -> PRELIMINAR — composición no conciliada (ver preguntas abajo)
A29: Preguntas abiertas
A30: 1. ¿A qué unidad corresponde la fila 'Cochera y dpto' (Gs 1.200.000)? ¿Es un departamento adicional, el local comercial u otro concepto?
A31: 2. ¿Dónde está incluido el alquiler del local comercial?
A32: 3. ¿Algún concepto agrupa varias unidades o duplica ingresos?
A33: 4. ¿Cuál es la fecha de vigencia de los alquileres y del tipo de cambio de Gs 6.100?
A34: 5. Contratos vigentes, ocupación real y cobro efectivo de los últimos 12 meses (extractos o recibos).
A35: 6. ¿La 'Cochera' (Gs 700.000) se alquila a un tercero ajeno al edificio? ¿Está incluida en la venta?

Sheet Ingresos_Gastos
A1: Ingresos y egresos — informados vs. pendientes
A2: Leyenda: azul = dato recibido (fuente: imágenes enviadas 2026-10-02); negro = fórmula; verde = vínculo a otra hoja; rojo itálica = PENDIENTE de confirmar (no es cero).
A4: Concepto | B4: Mensual | C4: Anual (USD) | D4: Estado | E4: Fuente / observación
A5: Ingreso mensual informado (Gs) | B5: =Alquileres_Unidad!H20 -> 19550000 | D5: Recibido (transcrito) | E5: Suma de la tabla; composición no conciliada (ver Conciliacion).
A6: Ingreso mensual USD (TC planilla) | B6: =B5/Parametros!$B$6 -> 3204.918 | D6: Calculado | E6: Gs mensual / tipo de cambio de la planilla (6.100).
A7: Ingreso bruto anual informado (USD) | C7: =B6*12 -> 38459.016 | D7: Calculado | E7: Supone 12 meses de cobro completo: sin vacancia ni morosidad (no verificado).
A9: Egresos informados en la planilla
A10: Impuesto anual | C10: =Parametros!$B$8 -> 2764 | D10: Recibido — alcance a confirmar | E10: No se informa qué impuesto(s) cubre (IVA, IRP, inmobiliario u otro). Ver Rentabilidad: equivale al 7,19% del bruto.
A11: Gastos anuales | C11: =Parametros!$B$9 -> 1200 | D11: Recibido — alcance a confirmar | E11: No se informa qué conceptos cubre.
A12: Total egresos informados | C12: =SUM(C10:C11) -> 3964
A14: Egresos NO informados (pendientes — no son cero)
A15: Mantenimiento y reparaciones | D15: PENDIENTE | E15: Celda vacía a propósito: completar con dato documentado.
A16: Administración del edificio / gestión de alquileres | D16: PENDIENTE | E16: Celda vacía a propósito: completar con dato documentado.
A17: Seguros | D17: PENDIENTE | E17: Celda vacía a propósito: completar con dato documentado.
A18: Vacancia (meses sin inquilino) | D18: PENDIENTE | E18: Celda vacía a propósito: completar con dato documentado.
A19: Morosidad / incobrables | D19: PENDIENTE | E19: Celda vacía a propósito: completar con dato documentado.
A20: Reserva para reposiciones (CAPEX) | D20: PENDIENTE | E20: Celda vacía a propósito: completar con dato documentado.
A21: Servicios a cargo del propietario (áreas comunes, agua, luz) | D21: PENDIENTE | E21: Celda vacía a propósito: completar con dato documentado.
A22: Impuesto inmobiliario (si no está incluido arriba) | D22: PENDIENTE | E22: Celda vacía a propósito: completar con dato documentado.
A23: Cantidad de egresos pendientes de dato | C23: =COUNTBLANK(C15:C22) -> 8
A25: Resultado neto según gastos informados (USD/año) | C25: =C7-C12 -> 34495.016 | E25: Solo descuenta los dos egresos de la planilla. NO es una renta neta definitiva.
A26: Resultado neto incluyendo egresos pendientes cargados (USD/año) | C26: =IF(C23>0,"Incompleto: faltan "&C23&" egresos",C7-C12-SUM(C15:C22)) -> Incompleto: faltan 8 egresos

Sheet Rentabilidad
A1: Rentabilidad — recálculo con precisión completa
A2: Leyenda: azul = dato recibido (fuente: imágenes enviadas 2026-10-02); negro = fórmula; verde = vínculo a otra hoja; rojo itálica = PENDIENTE de confirmar (no es cero).
A4: Indicador | B4: Recalculado | C4: Planilla recibida | D4: Diferencia | E4: Base de cálculo
A5: Ingreso mensual (USD) | B5: =Ingresos_Gastos!B6 -> 3204.918 | C5: =Parametros!$B$10 -> 3205 | D5: =B5-C5 -> -0.081967213 | E5: Gs 19.550.000 / 6.100
A6: Ingreso bruto anual (USD) | B6: =Ingresos_Gastos!C7 -> 38459.016 | C6: =Parametros!$B$11 -> 38459 | D6: =B6-C6 -> 0.016393443 | E6: Ingreso mensual USD × 12
A7: Resultado neto según gastos informados (USD) | B7: =Ingresos_Gastos!$C$25 -> 34495.016 | C7: =Parametros!$B$12 -> 34495 | D7: =B7-C7 -> 0.016393443 | E7: Bruto − impuesto (2.764) − gastos (1.200)
A8: Rentabilidad bruta sobre precio | B8: =B6/Parametros!$B$5 -> 0.11311475 | C8: =Parametros!$B$13 -> 0.113 | D8: =B8-C8 -> 0.0001147541 | E8: Bruto anual / precio de venta (USD 340.000)
A9: Rentabilidad neta según gastos informados, sobre precio | B9: =B7/Parametros!$B$5 -> 0.10145593 | C9: =Parametros!$B$14 -> 0.1015 | D9: =B9-C9 -> -4.4069431e-05 | E9: Resultado neto / precio de venta. Sin gastos de adquisición en el denominador.
A11: Observaciones de la auditoría
A12: Impuesto anual / ingreso bruto anual | B12: =Parametros!$B$8/B6 -> 0.071868713 | E12: No coincide con 5% ni 10% del bruto: la composición del impuesto debe confirmarse.
A13: Ingreso anual de la descripción comercial (USD) | B13: =Parametros!$B$15 -> 34500 | C13: =B7 -> 34495.016 | D13: =B13-C13 -> 4.9836066 | E13: Los USD 34.500 de la descripción son el resultado NETO redondeado, no el ingreso bruto (USD 38.459).
A14: Relación 'bruta' de la descripción (10,15%) | B14: =B9 -> 0.10145593 | E14: El 10,15% es rentabilidad NETA según gastos informados, no bruta. La bruta es 11,31%.
A15: Precio implícito por departamento (USD, referencia) | B15: =Parametros!$B$5/Conciliacion!C11 -> 26153.846 | E15: Precio total / 13 departamentos. Solo referencia aritmética: no es tasación ni valor por unidad.
A16: Múltiplo precio / ingreso bruto anual (veces) | B16: =Parametros!$B$5/B6 -> 8.8405797 | E16: Años de ingreso bruto informado equivalentes al precio, sin egresos ni vacancia.
A17: Escenario de tipo de cambio
A18: Escenario | B18: TC (Gs/USD) | C18: Bruto anual (USD) | D18: Rent. bruta | E18: Rent. neta según gastos informados / Fuente
A19: Original — planilla recibida | B19: =Parametros!$B$6 -> 6100 | C19: =Ingresos_Gastos!B5*12/B19 -> 38459.016 | D19: =C19/Parametros!$B$5 -> 0.11311475 | E19: =(C19-Ingresos_Gastos!C12)/Parametros!$B$5 -> 0.10145593
A20: Actualizado — TC autorizado (pendiente) | B20: =IF(ISBLANK(Parametros!$B$20),"PENDIENTE",Parametros!$B$20) -> PENDIENTE | C20: =IF(ISNUMBER(B20),Ingresos_Gastos!B5*12/B20,"PENDIENTE") -> PENDIENTE | D20: =IF(ISNUMBER(C20),C20/Parametros!$B$5,"PENDIENTE") -> PENDIENTE | E20: =IF(ISNUMBER(C20),"Fuente: "&Parametros!$B$21,"Cargar TC y fuente en Parametros!B20:B21") -> Cargar TC y fuente en Parametros!B20:B21
A21: Nota: impuesto y gastos se mantienen en USD fijos en ambos escenarios (así figuran en la planilla). Las cifras son indicadores sobre el precio de venta, no retorno sobre inversión total ni rentabilidad garantizada.

Sheet Parametros
A1: Parámetros — datos recibidos (sin modificar)
A2: Leyenda: azul = dato recibido (fuente: imágenes enviadas 2026-10-02); negro = fórmula; verde = vínculo a otra hoja; rojo itálica = PENDIENTE de confirmar (no es cero).
A4: Parámetro | B4: Valor | C4: Estado | D4: Fuente / observación
A5: Precio de venta (USD) | B5: 340000 | C5: Recibido | D5: Pedido del founder + planilla de rentabilidad (celda 'Precio USD').
A6: Tipo de cambio de la planilla (Gs por USD) | B6: 6100 | C6: Recibido | D6: Planilla de rentabilidad y detalle de alquileres. Fecha de vigencia NO informada; no es cotización actual.
A7: Total mensual indicado en el detalle (Gs) | B7: 19550000 | C7: Recibido | D7: Fila 'TOTAL' del detalle de alquileres.
A8: Impuesto anual informado (USD) | B8: 2764 | C8: Recibido | D8: Planilla de rentabilidad. Qué impuesto(s) cubre: PENDIENTE.
A9: Gastos anuales informados (USD) | B9: 1200 | C9: Recibido | D9: Planilla de rentabilidad. Qué conceptos cubre: PENDIENTE.
A10: Ingreso mensual USD indicado en planilla | B10: 3205 | C10: Recibido | D10: Planilla de rentabilidad (redondeado en la fuente).
A11: Ingreso bruto anual USD indicado en planilla | B11: 38459 | C11: Recibido | D11: Planilla de rentabilidad, columna 'USD Anual'.
A12: Renta neta anual USD indicada en planilla | B12: 34495 | C12: Recibido | D12: Planilla de rentabilidad.
A13: Rentabilidad bruta indicada en planilla | B13: 0.113 | C13: Recibido | D13: Texto 'Bruta (11,3%)' de la planilla.
A14: Rentabilidad neta indicada en planilla | B14: 0.1015 | C14: Recibido | D14: Celda 'Renta Anual Neta 10,15%' de la planilla.
A15: Ingreso anual mencionado en la descripción comercial (USD) | B15: 34500 | C15: Recibido | D15: Descripción del aviso: 'ingresos anuales aprox. USD 34.500' — corresponde al resultado NETO de la planilla, no al bruto.
A16: Departamentos de 1 dormitorio (mix comercial) | B16: 6 | C16: Recibido | D16: Descripción comercial.
... A19: Locales comerciales (mix comercial) | B19: 1 | C19: Recibido | D19: Descripción comercial.
A20: Tipo de cambio alternativo autorizado (Gs por USD) | C20: PENDIENTE | D20: Vacío a propósito: cargar solo una cotización autorizada y verificable, con fuente y fecha en la fila siguiente.
A21: Fuente y fecha del tipo de cambio alternativo | C21: PENDIENTE | D21: Ej.: 'BCP, cotización de referencia, dd/mm/aaaa'.
